devs_webhook/__init__.py
devs_webhook/app.py
devs_webhook/config.py
devs_webhook/main_cli.py
devs_webhook/cli/__init__.py
devs_webhook/cli/worker.py
devs_webhook/core/__init__.py
devs_webhook/core/base_dispatcher.py
devs_webhook/core/claude_dispatcher.py
devs_webhook/core/container_pool.py
devs_webhook/core/deduplication.py
devs_webhook/core/repository_manager.py
devs_webhook/core/task_processor.py
devs_webhook/core/test_dispatcher.py
devs_webhook/core/webhook_config.py
devs_webhook/core/webhook_handler.py
devs_webhook/github/__init__.py
devs_webhook/github/app_auth.py
devs_webhook/github/client.py
devs_webhook/github/models.py
devs_webhook/github/parser.py
devs_webhook/sources/__init__.py
devs_webhook/sources/base.py
devs_webhook/sources/sqs_source.py
devs_webhook/sources/webhook_source.py
devs_webhook/utils/__init__.py
devs_webhook/utils/async_utils.py
devs_webhook/utils/container_logs.py
devs_webhook/utils/github.py
devs_webhook/utils/logging.py
devs_webhook/utils/s3_artifacts.py
devs_webhook/utils/serialization.py
devs_webhook-1.2.1.dist-info/licenses/LICENSE
devs_webhook-1.2.1.dist-info/METADATA
devs_webhook-1.2.1.dist-info/WHEEL
devs_webhook-1.2.1.dist-info/entry_points.txt
devs_webhook-1.2.1.dist-info/top_level.txt
devs_webhook-1.2.1.dist-info/RECORD
