Metadata-Version: 2.4
Name: devs-webhook
Version: 1.2.1
Summary: GitHub webhook handler for automated devcontainer operations with Claude Code
Author: Dan Lester
License-Expression: MIT
Project-URL: Homepage, https://github.com/ideonate/devs
Project-URL: Repository, https://github.com/ideonate/devs
Project-URL: Issues, https://github.com/ideonate/devs/issues
Project-URL: Documentation, https://github.com/ideonate/devs/tree/main/packages/webhook
Keywords: webhook,github,devcontainer,claude,automation
Classifier: Development Status :: 4 - Beta
Classifier: Environment :: Web Environment
Classifier: Framework :: FastAPI
Classifier: Intended Audience :: Developers
Classifier: Operating System :: OS Independent
Classifier: Programming Language :: Python :: 3
Classifier: Programming Language :: Python :: 3.8
Classifier: Programming Language :: Python :: 3.9
Classifier: Programming Language :: Python :: 3.10
Classifier: Programming Language :: Python :: 3.11
Classifier: Programming Language :: Python :: 3.12
Classifier: Topic :: Software Development :: Libraries :: Python Modules
Classifier: Topic :: Internet :: WWW/HTTP :: WSGI :: Application
Requires-Python: >=3.8
License-File: LICENSE
Requires-Dist: fastapi>=0.68.0
Requires-Dist: uvicorn[standard]>=0.15.0
Requires-Dist: pydantic>=2.0.0
Requires-Dist: pydantic-settings>=2.0.0
Requires-Dist: httpx>=0.24.0
Requires-Dist: GitPython>=3.1.0
Requires-Dist: PyGithub>=1.55.0
Requires-Dist: cryptography>=3.4.0
Requires-Dist: PyJWT>=2.0.0
Requires-Dist: structlog>=21.1.0
Requires-Dist: tenacity>=8.0.0
Requires-Dist: click>=8.0.0
Requires-Dist: devs-common>=0.1.0
Provides-Extra: sqs
Requires-Dist: boto3>=1.18.0; extra == "sqs"
Provides-Extra: all
Requires-Dist: boto3>=1.18.0; extra == "all"
Provides-Extra: dev
Requires-Dist: pytest>=6.0; extra == "dev"
Requires-Dist: pytest-cov; extra == "dev"
Requires-Dist: pytest-asyncio; extra == "dev"
Requires-Dist: black; extra == "dev"
Requires-Dist: mypy; extra == "dev"
Requires-Dist: flake8; extra == "dev"
Requires-Dist: httpx; extra == "dev"
Requires-Dist: boto3>=1.18.0; extra == "dev"
Requires-Dist: build>=0.10.0; extra == "dev"
Requires-Dist: twine>=4.0.0; extra == "dev"
Dynamic: license-file
